Metadata-Version: 2.1
Name: fast-dev-cli
Version: 0.20.1
Summary: Python project development tool.
Author-Email: Waket Zheng <waketzheng@gmail.com>>
Classifier: Development Status :: 4 - Beta
Classifier: Intended Audience :: Developers
Classifier: Intended Audience :: Science/Research
Classifier: Intended Audience :: System Administrators
Classifier: Operating System :: OS Independent
Classifier: Programming Language :: Python :: 3 :: Only
Classifier: Programming Language :: Python :: 3.10
Classifier: Programming Language :: Python :: 3.11
Classifier: Programming Language :: Python :: 3.12
Classifier: Programming Language :: Python :: 3.13
Classifier: Programming Language :: Python :: 3.14
Classifier: Topic :: Software Development :: Libraries :: Python Modules
Classifier: Topic :: Software Development :: Libraries
Classifier: Topic :: Software Development
Classifier: Typing :: Typed
Classifier: License :: OSI Approved :: MIT License
Project-URL: Homepage, https://github.com/waketzheng/fast-dev-cli
Requires-Python: >=3.10
Requires-Dist: typer-slim<1,>=0.12.3
Requires-Dist: tomli<3,>=2.0.1; python_version < "3.11"
Requires-Dist: emoji>=2.12.1
Requires-Dist: packaging>=20.5
Requires-Dist: coverage>=7.5.1
Requires-Dist: pytest>=8.2.0
Provides-Extra: include-optional-dependencies
Requires-Dist: all; extra == "include-optional-dependencies"
